[
	{
		"inputs": [],
		"name": "getTotalStakes",
		"outputs": [
			{
				"internalType": "uint256",
				"name": "_totalStakes",
				"type": "uint256"
			}
		],
		"stateMutability": "view",
		"type": "function"
	},
	{
		"inputs": [
			{
				"internalType": "address",
				"name": "who",
				"type": "address"
			},
			{
				"internalType": "uint256",
				"name": "timestamp",
				"type": "uint256"
			}
		],
		"name": "getWeightAt",
		"outputs": [
			{
				"internalType": "uint256",
				"name": "weight",
				"type": "uint256"
			}
		],
		"stateMutability": "view",
		"type": "function"
	}
]
